diffsims/__init__.py
diffsims/conftest.py
diffsims/constants.py
diffsims/release_info.py
diffsims/crystallography/__init__.py
diffsims/crystallography/_diffracting_vector.py
diffsims/crystallography/get_hkl.py
diffsims/crystallography/reciprocal_lattice_vector.py
diffsims/generators/__init__.py
diffsims/generators/diffraction_generator.py
diffsims/generators/library_generator.py
diffsims/generators/rotation_list_generators.py
diffsims/generators/simulation_generator.py
diffsims/generators/sphere_mesh_generators.py
diffsims/generators/zap_map_generator.py
diffsims/libraries/__init__.py
diffsims/libraries/diffraction_library.py
diffsims/libraries/structure_library.py
diffsims/libraries/vector_library.py
diffsims/pattern/__init__.py
diffsims/pattern/detector_functions.py
diffsims/sims/__init__.py
diffsims/sims/diffraction_simulation.py
diffsims/simulations/__init__.py
diffsims/simulations/simulation1d.py
diffsims/simulations/simulation2d.py
diffsims/structure_factor/__init__.py
diffsims/structure_factor/atomic_scattering_factor.py
diffsims/structure_factor/atomic_scattering_parameters.py
diffsims/structure_factor/structure_factor.py
diffsims/tests/__init__.py
diffsims/tests/crystallography/__init__.py
diffsims/tests/crystallography/test_diffracting_vector.py
diffsims/tests/crystallography/test_get_hkl.py
diffsims/tests/crystallography/test_reciprocal_lattice_vector.py
diffsims/tests/generators/__init__.py
diffsims/tests/generators/test_diffraction_generator.py
diffsims/tests/generators/test_library_generator.py
diffsims/tests/generators/test_rotation_list_generator.py
diffsims/tests/generators/test_simulation_generator.py
diffsims/tests/generators/test_sphere_mesh_generators.py
diffsims/tests/generators/test_zap_map_generator.py
diffsims/tests/library/__init__.py
diffsims/tests/library/test_diffraction_library.py
diffsims/tests/library/test_structure_library.py
diffsims/tests/library/test_vector_library.py
diffsims/tests/patterns/__init__.py
diffsims-0.7.0.dist-info/licenses/LICENSE
diffsims-0.7.0.dist-info/METADATA
diffsims-0.7.0.dist-info/WHEEL
diffsims-0.7.0.dist-info/top_level.txt
diffsims-0.7.0.dist-info/RECORD
