Metadata-Version: 2.4
Name: diffsims
Version: 0.7.0
Summary: Diffraction Simulations in Python
Home-page: https://github.com/pyxem/diffsims
Author: Duncan Johnstone, Phillip Crout
Author-email: pyxem.team@gmail.com
License: GPLv3+
Classifier: Programming Language :: Python :: 3
Classifier: Programming Language :: Python :: 3.8
Classifier: Programming Language :: Python :: 3.9
Classifier: Programming Language :: Python :: 3.10
Classifier: Programming Language :: Python :: 3.11
Classifier: Development Status :: 4 - Beta
Classifier: Intended Audience :: Science/Research
Classifier: License :: OSI Approved :: GNU General Public License v3 or later (GPLv3+)
Classifier: Natural Language :: English
Classifier: Operating System :: OS Independent
Classifier: Topic :: Scientific/Engineering
Classifier: Topic :: Scientific/Engineering :: Physics
Requires-Python: >=3.6
License-File: LICENSE
Requires-Dist: diffpy.structure>=3.0.2
Requires-Dist: matplotlib>=3.3
Requires-Dist: numba
Requires-Dist: numpy>=1.17.3
Requires-Dist: orix>=0.12.1
Requires-Dist: psutil
Requires-Dist: scipy>=1.8
Requires-Dist: tqdm>=4.9
Requires-Dist: transforms3d
Provides-Extra: doc
Requires-Dist: numpydoc; extra == "doc"
Requires-Dist: pydata-sphinx-theme; extra == "doc"
Requires-Dist: sphinx>=3.0.2; extra == "doc"
Requires-Dist: sphinx-design; extra == "doc"
Requires-Dist: sphinx_gallery; extra == "doc"
Provides-Extra: tests
Requires-Dist: coverage>=5.0; extra == "tests"
Requires-Dist: pytest>=5.4; extra == "tests"
Requires-Dist: pytest-cov>=2.8.1; extra == "tests"
Requires-Dist: pytest-xdist; extra == "tests"
Provides-Extra: dev
Requires-Dist: black>=23.1; extra == "dev"
Requires-Dist: manifix; extra == "dev"
Requires-Dist: pre-commit>=1.16; extra == "dev"
Requires-Dist: numpydoc; extra == "dev"
Requires-Dist: pydata-sphinx-theme; extra == "dev"
Requires-Dist: sphinx>=3.0.2; extra == "dev"
Requires-Dist: sphinx-design; extra == "dev"
Requires-Dist: sphinx_gallery; extra == "dev"
Requires-Dist: coverage>=5.0; extra == "dev"
Requires-Dist: pytest>=5.4; extra == "dev"
Requires-Dist: pytest-cov>=2.8.1; extra == "dev"
Requires-Dist: pytest-xdist; extra == "dev"
Dynamic: author
Dynamic: author-email
Dynamic: classifier
Dynamic: description
Dynamic: home-page
Dynamic: license
Dynamic: license-file
Dynamic: provides-extra
Dynamic: requires-dist
Dynamic: requires-python
Dynamic: summary
